[{"key":"window","proto":"window","instance":"window","props":["Infinity","NaN","undefined","globalThis","JSON","Math","Intl","Atomics","Reflect","console","CSS","window","self","document","name","location","customElements","history","navigation","locationbar","menubar","personalbar","scrollbars","statusbar","toolbar","status","closed","frames","length","top","opener","parent","frameElement","navigator","origin","external","screen","innerWidth","innerHeight","scrollX","pageXOffset","scrollY","pageYOffset","visualViewport","screenX","screenY","outerWidth","outerHeight","devicePixelRatio","event","clientInformation","offscreenBuffering","screenLeft","screenTop","styleMedia","onsearch","isSecureContext","trustedTypes","performance","onappinstalled","onbeforeinstallprompt","crypto","indexedDB","sessionStorage","localStorage","onbeforexrselect","onabort","onbeforeinput","onblur","oncancel","oncanplay","oncanplaythrough","onchange","onclick","onclose","oncontextlost","oncontextmenu","oncontextrestored","oncuechange","ondblclick","ondrag","ondragend","ondragenter","ondragleave","ondragover","ondragstart","ondrop","ondurationchange","onemptied","onended","onerror","onfocus","onformdata","oninput","oninvalid","onkeydown","onkeypress","onkeyup","onload","onloadeddata","onloadedmetadata","onloadstart","onmousedown","onmouseenter","onmouseleave","onmousemove","onmouseout","onmouseover","onmouseup","onmousewheel","onpause","onplay","onplaying","onprogress","onratechange","onreset","onresize","onscroll","onsecuritypolicyviolation","onseeked","onseeking","onselect","onslotchange","onstalled","onsubmit","onsuspend","ontimeupdate","ontoggle","onvolumechange","onwaiting","onwebkitanimationend","onwebkitanimationiteration","onwebkitanimationstart","onwebkittransitionend","onwheel","onauxclick","ongotpointercapture","onlostpointercapture","onpointerdown","onpointermove","onpointerrawupdate","onpointerup","onpointercancel","onpointerover","onpointerout","onpointerenter","onpointerleave","onselectstart","onselectionchange","onanimationend","onanimationiteration","onanimationstart","ontransitionrun","ontransitionstart","ontransitionend","ontransitioncancel","onafterprint","onbeforeprint","onbeforeunload","onhashchange","onlanguagechange","onmessage","onmessageerror","onoffline","ononline","onpagehide","onpageshow","onpopstate","onrejectionhandled","onstorage","onunhandledrejection","onunload","crossOriginIsolated","scheduler","chrome","WebAssembly","caches","cookieStore","ondevicemotion","ondeviceorientation","ondeviceorientationabsolute","launchQueue","documentPictureInPicture","onbeforematch","onbeforetoggle","GPUBufferUsage","GPUColorWrite","GPUMapMode","GPUShaderStage","GPUTextureUsage","originAgentCluster","credentialless","speechSynthesis","oncontentvisibilityautostatechange","onscrollend"],"methods":["Object","Function","Array","Number","parseFloat","parseInt","Boolean","String","Symbol","Date","Promise","RegExp","Error","AggregateError","EvalError","RangeError","ReferenceError","SyntaxError","TypeError","URIError","ArrayBuffer","Uint8Array","Int8Array","Uint16Array","Int16Array","Uint32Array","Int32Array","Float32Array","Float64Array","Uint8ClampedArray","BigUint64Array","BigInt64Array","DataView","Map","BigInt","Set","WeakMap","WeakSet","Proxy","FinalizationRegistry","WeakRef","decodeURI","decodeURIComponent","encodeURI","encodeURIComponent","escape","unescape","eval","isFinite","isNaN","Option","Image","Audio","webkitURL","webkitRTCPeerConnection","webkitMediaStream","WebKitMutationObserver","WebKitCSSMatrix","XSLTProcessor","XPathResult","XPathExpression","XPathEvaluator","XMLSerializer","XMLHttpRequestUpload","XMLHttpRequestEventTarget","XMLHttpRequest","XMLDocument","WritableStreamDefaultWriter","WritableStreamDefaultController","WritableStream","Worker","Window","WheelEvent","WebSocket","WebGLVertexArrayObject","WebGLUniformLocation","WebGLTransformFeedback","WebGLTexture","WebGLSync","WebGLShaderPrecisionFormat","WebGLShader","WebGLSampler","WebGLRenderingContext","WebGLRenderbuffer","WebGLQuery","WebGLProgram","WebGLFramebuffer","WebGLContextEvent","WebGLBuffer","WebGLActiveInfo","WebGL2RenderingContext","WaveShaperNode","VisualViewport","VirtualKeyboardGeometryChangeEvent","ValidityState","VTTCue","UserActivation","URLSearchParams","URLPattern","URL","UIEvent","TrustedTypePolicyFactory","TrustedTypePolicy","TrustedScriptURL","TrustedScript","TrustedHTML","TreeWalker","TransitionEvent","TransformStreamDefaultController","TransformStream","TrackEvent","TouchList","TouchEvent","Touch","TimeRanges","TextTrackList","TextTrackCueList","TextTrackCue","TextTrack","TextMetrics","TextEvent","TextEncoderStream","TextEncoder","TextDecoderStream","TextDecoder","Text","TaskSignal","TaskPriorityChangeEvent","TaskController","TaskAttributionTiming","SyncManager","SubmitEvent","StyleSheetList","StyleSheet","StylePropertyMapReadOnly","StylePropertyMap","StorageEvent","Storage","StereoPannerNode","StaticRange","SourceBufferList","SourceBuffer","ShadowRoot","Selection","SecurityPolicyViolationEvent","ScriptProcessorNode","ScreenOrientation","Screen","Scheduling","Scheduler","SVGViewElement","SVGUseElement","SVGUnitTypes","SVGTransformList","SVGTransform","SVGTitleElement","SVGTextPositioningElement","SVGTextPathElement","SVGTextElement","SVGTextContentElement","SVGTSpanElement","SVGSymbolElement","SVGSwitchElement","SVGStyleElement","SVGStringList","SVGStopElement","SVGSetElement","SVGScriptElement","SVGSVGElement","SVGRectElement","SVGRect","SVGRadialGradientElement","SVGPreserveAspectRatio","SVGPolylineElement","SVGPolygonElement","SVGPointList","SVGPoint","SVGPatternElement","SVGPathElement","SVGNumberList","SVGNumber","SVGMetadataElement","SVGMatrix","SVGMaskElement","SVGMarkerElement","SVGMPathElement","SVGLinearGradientElement","SVGLineElement","SVGLengthList","SVGLength","SVGImageElement","SVGGraphicsElement","SVGGradientElement","SVGGeometryElement","SVGGElement","SVGForeignObjectElement","SVGFilterElement","SVGFETurbulenceElement","SVGFETileElement","SVGFESpotLightElement","SVGFESpecularLightingElement","SVGFEPointLightElement","SVGFEOffsetElement","SVGFEMorphologyElement","SVGFEMergeNodeElement","SVGFEMergeElement","SVGFEImageElement","SVGFEGaussianBlurElement","SVGFEFuncRElement","SVGFEFuncGElement","SVGFEFuncBElement","SVGFEFuncAElement","SVGFEFloodElement","SVGFEDropShadowElement","SVGFEDistantLightElement","SVGFEDisplacementMapElement","SVGFEDiffuseLightingElement","SVGFEConvolveMatrixElement","SVGFECompositeElement","SVGFEComponentTransferElement","SVGFEColorMatrixElement","SVGFEBlendElement","SVGEllipseElement","SVGElement","SVGDescElement","SVGDefsElement","SVGComponentTransferFunctionElement","SVGClipPathElement","SVGCircleElement","SVGAnimationElement","SVGAnimatedTransformList","SVGAnimatedString","SVGAnimatedRect","SVGAnimatedPreserveAspectRatio","SVGAnimatedNumberList","SVGAnimatedNumber","SVGAnimatedLengthList","SVGAnimatedLength","SVGAnimatedInteger","SVGAnimatedEnumeration","SVGAnimatedBoolean","SVGAnimatedAngle","SVGAnimateTransformElement","SVGAnimateMotionElement","SVGAnimateElement","SVGAngle","SVGAElement","Response","ResizeObserverSize","ResizeObserverEntry","ResizeObserver","Request","ReportingObserver","ReadableStreamDefaultReader","ReadableStreamDefaultController","ReadableStreamBYOBRequest","ReadableStreamBYOBReader","ReadableStream","ReadableByteStreamController","Range","RadioNodeList","RTCTrackEvent","RTCStatsReport","RTCSessionDescription","RTCSctpTransport","RTCRtpTransceiver","RTCRtpSender","RTCRtpReceiver","RTCPeerConnectionIceEvent","RTCPeerConnectionIceErrorEvent","RTCPeerConnection","RTCIceTransport","RTCIceCandidate","RTCErrorEvent","RTCError","RTCEncodedVideoFrame","RTCEncodedAudioFrame","RTCDtlsTransport","RTCDataChannelEvent","RTCDataChannel","RTCDTMFToneChangeEvent","RTCDTMFSender","RTCCertificate","PromiseRejectionEvent","ProgressEvent","Profiler","ProcessingInstruction","PopStateEvent","PointerEvent","PluginArray","Plugin","PictureInPictureWindow","PictureInPictureEvent","PeriodicWave","PerformanceTiming","PerformanceServerTiming","PerformanceResourceTiming","PerformancePaintTiming","PerformanceObserverEntryList","PerformanceObserver","PerformanceNavigationTiming","PerformanceNavigation","PerformanceMeasure","PerformanceMark","PerformanceLongTaskTiming","PerformanceEventTiming","PerformanceEntry","PerformanceElementTiming","Performance","Path2D","PannerNode","PageTransitionEvent","OverconstrainedError","OscillatorNode","OffscreenCanvasRenderingContext2D","OffscreenCanvas","OfflineAudioContext","OfflineAudioCompletionEvent","NodeList","NodeIterator","NodeFilter","Node","NetworkInformation","Navigator","NavigationTransition","NavigationHistoryEntry","NavigationDestination","NavigationCurrentEntryChangeEvent","Navigation","NavigateEvent","NamedNodeMap","MutationRecord","MutationObserver","MouseEvent","MimeTypeArray","MimeType","MessagePort","MessageEvent","MessageChannel","MediaStreamTrackProcessor","MediaStreamTrackGenerator","MediaStreamTrackEvent","MediaStreamTrack","MediaStreamEvent","MediaStreamAudioSourceNode","MediaStreamAudioDestinationNode","MediaStream","MediaSourceHandle","MediaSource","MediaRecorder","MediaQueryListEvent","MediaQueryList","MediaList","MediaError","MediaEncryptedEvent","MediaElementAudioSourceNode","MediaCapabilities","MathMLElement","Location","LayoutShiftAttribution","LayoutShift","LargestContentfulPaint","KeyframeEffect","KeyboardEvent","IntersectionObserverEntry","IntersectionObserver","InputEvent","InputDeviceInfo","InputDeviceCapabilities","ImageData","ImageCapture","ImageBitmapRenderingContext","ImageBitmap","IdleDeadline","IIRFilterNode","IDBVersionChangeEvent","IDBTransaction","IDBRequest","IDBOpenDBRequest","IDBObjectStore","IDBKeyRange","IDBIndex","IDBFactory","IDBDatabase","IDBCursorWithValue","IDBCursor","History","Headers","HashChangeEvent","HTMLVideoElement","HTMLUnknownElement","HTMLUListElement","HTMLTrackElement","HTMLTitleElement","HTMLTimeElement","HTMLTextAreaElement","HTMLTemplateElement","HTMLTableSectionElement","HTMLTableRowElement","HTMLTableElement","HTMLTableColElement","HTMLTableCellElement","HTMLTableCaptionElement","HTMLStyleElement","HTMLSpanElement","HTMLSourceElement","HTMLSlotElement","HTMLSelectElement","HTMLScriptElement","HTMLQuoteElement","HTMLProgressElement","HTMLPreElement","HTMLPictureElement","HTMLParamElement","HTMLParagraphElement","HTMLOutputElement","HTMLOptionsCollection","HTMLOptionElement","HTMLOptGroupElement","HTMLObjectElement","HTMLOListElement","HTMLModElement","HTMLMeterElement","HTMLMetaElement","HTMLMenuElement","HTMLMediaElement","HTMLMarqueeElement","HTMLMapElement","HTMLLinkElement","HTMLLegendElement","HTMLLabelElement","HTMLLIElement","HTMLInputElement","HTMLImageElement","HTMLIFrameElement","HTMLHtmlElement","HTMLHeadingElement","HTMLHeadElement","HTMLHRElement","HTMLFrameSetElement","HTMLFrameElement","HTMLFormElement","HTMLFormControlsCollection","HTMLFontElement","HTMLFieldSetElement","HTMLEmbedElement","HTMLElement","HTMLDocument","HTMLDivElement","HTMLDirectoryElement","HTMLDialogElement","HTMLDetailsElement","HTMLDataListElement","HTMLDataElement","HTMLDListElement","HTMLCollection","HTMLCanvasElement","HTMLButtonElement","HTMLBodyElement","HTMLBaseElement","HTMLBRElement","HTMLAudioElement","HTMLAreaElement","HTMLAnchorElement","HTMLAllCollection","GeolocationPositionError","GeolocationPosition","GeolocationCoordinates","Geolocation","GamepadHapticActuator","GamepadEvent","GamepadButton","Gamepad","GainNode","FormDataEvent","FormData","FontFaceSetLoadEvent","FontFace","FocusEvent","FileReader","FileList","File","FeaturePolicy","External","EventTarget","EventSource","EventCounts","Event","ErrorEvent","ElementInternals","Element","DynamicsCompressorNode","DragEvent","DocumentType","DocumentFragment","Document","DelayNode","DecompressionStream","DataTransferItemList","DataTransferItem","DataTransfer","DOMTokenList","DOMStringMap","DOMStringList","DOMRectReadOnly","DOMRectList","DOMRect","DOMQuad","DOMPointReadOnly","DOMPoint","DOMParser","DOMMatrixReadOnly","DOMMatrix","DOMImplementation","DOMException","DOMError","CustomStateSet","CustomEvent","CustomElementRegistry","Crypto","CountQueuingStrategy","ConvolverNode","ConstantSourceNode","CompressionStream","CompositionEvent","Comment","CloseEvent","ClipboardEvent","CharacterData","ChannelSplitterNode","ChannelMergerNode","CanvasRenderingContext2D","CanvasPattern","CanvasGradient","CanvasCaptureMediaStreamTrack","CSSVariableReferenceValue","CSSUnparsedValue","CSSUnitValue","CSSTranslate","CSSTransformValue","CSSTransformComponent","CSSSupportsRule","CSSStyleValue","CSSStyleSheet","CSSStyleRule","CSSStyleDeclaration","CSSSkewY","CSSSkewX","CSSSkew","CSSScale","CSSRuleList","CSSRule","CSSRotate","CSSPropertyRule","CSSPositionValue","CSSPerspective","CSSPageRule","CSSNumericValue","CSSNumericArray","CSSNamespaceRule","CSSMediaRule","CSSMatrixComponent","CSSMathValue","CSSMathSum","CSSMathProduct","CSSMathNegate","CSSMathMin","CSSMathMax","CSSMathInvert","CSSMathClamp","CSSLayerStatementRule","CSSLayerBlockRule","CSSKeywordValue","CSSKeyframesRule","CSSKeyframeRule","CSSImportRule","CSSImageValue","CSSGroupingRule","CSSFontPaletteValuesRule","CSSFontFaceRule","CSSCounterStyleRule","CSSContainerRule","CSSConditionRule","CDATASection","ByteLengthQueuingStrategy","BroadcastChannel","BlobEvent","Blob","BiquadFilterNode","BeforeUnloadEvent","BeforeInstallPromptEvent","BaseAudioContext","BarProp","AudioWorkletNode","AudioSinkInfo","AudioScheduledSourceNode","AudioProcessingEvent","AudioParamMap","AudioParam","AudioNode","AudioListener","AudioDestinationNode","AudioContext","AudioBufferSourceNode","AudioBuffer","Attr","AnimationEvent","AnimationEffect","Animation","AnalyserNode","AbstractRange","AbortSignal","AbortController","alert","atob","blur","btoa","cancelAnimationFrame","cancelIdleCallback","captureEvents","clearInterval","clearTimeout","close","confirm","createImageBitmap","fetch","find","focus","getComputedStyle","getSelection","matchMedia","moveBy","moveTo","open","postMessage","print","prompt","queueMicrotask","releaseEvents","reportError","requestAnimationFrame","requestIdleCallback","resizeBy","resizeTo","scroll","scrollBy","scrollTo","setInterval","setTimeout","stop","structuredClone","webkitCancelAnimationFrame","webkitRequestAnimationFrame","AbsoluteOrientationSensor","Accelerometer","AudioWorklet","BatteryManager","Cache","CacheStorage","Clipboard","ClipboardItem","CookieChangeEvent","CookieStore","CookieStoreManager","Credential","CredentialsContainer","CryptoKey","DeviceMotionEvent","DeviceMotionEventAcceleration","DeviceMotionEventRotationRate","DeviceOrientationEvent","FederatedCredential","GPU","GPUAdapter","GPUAdapterInfo","GPUBindGroup","GPUBindGroupLayout","GPUBuffer","GPUCanvasContext","GPUCommandBuffer","GPUCommandEncoder","GPUCompilationInfo","GPUCompilationMessage","GPUComputePassEncoder","GPUComputePipeline","GPUDevice","GPUDeviceLostInfo","GPUError","GPUExternalTexture","GPUInternalError","GPUOutOfMemoryError","GPUPipelineError","GPUPipelineLayout","GPUQuerySet","GPUQueue","GPURenderBundle","GPURenderBundleEncoder","GPURenderPassEncoder","GPURenderPipeline","GPUSampler","GPUShaderModule","GPUSupportedFeatures","GPUSupportedLimits","GPUTexture","GPUTextureView","GPUUncapturedErrorEvent","GPUValidationError","GravitySensor","Gyroscope","Keyboard","KeyboardLayoutMap","LinearAccelerationSensor","Lock","LockManager","MIDIAccess","MIDIConnectionEvent","MIDIInput","MIDIInputMap","MIDIMessageEvent","MIDIOutput","MIDIOutputMap","MIDIPort","MediaDeviceInfo","MediaDevices","MediaKeyMessageEvent","MediaKeySession","MediaKeyStatusMap","MediaKeySystemAccess","MediaKeys","NavigationPreloadManager","NavigatorManagedData","OrientationSensor","PasswordCredential","RelativeOrientationSensor","Sanitizer","ScreenDetailed","ScreenDetails","Sensor","SensorErrorEvent","ServiceWorker","ServiceWorkerContainer","ServiceWorkerRegistration","StorageManager","SubtleCrypto","VirtualKeyboard","WGSLLanguageFeatures","WebTransport","WebTransportBidirectionalStream","WebTransportDatagramDuplexStream","WebTransportError","Worklet","XRDOMOverlayState","XRLayer","XRWebGLBinding","AudioData","EncodedAudioChunk","EncodedVideoChunk","ImageTrack","ImageTrackList","VideoColorSpace","VideoFrame","AudioDecoder","AudioEncoder","ImageDecoder","VideoDecoder","VideoEncoder","AuthenticatorAssertionResponse","AuthenticatorAttestationResponse","AuthenticatorResponse","PublicKeyCredential","Bluetooth","BluetoothCharacteristicProperties","BluetoothDevice","BluetoothRemoteGATTCharacteristic","BluetoothRemoteGATTDescriptor","BluetoothRemoteGATTServer","BluetoothRemoteGATTService","CaptureController","DelegatedInkTrailPresenter","Ink","DocumentPictureInPicture","EyeDropper","FileSystemDirectoryHandle","FileSystemFileHandle","FileSystemHandle","FileSystemWritableFileStream","FontData","FragmentDirective","HID","HIDConnectionEvent","HIDDevice","HIDInputReportEvent","IdentityCredential","IdentityProvider","IdleDetector","LaunchParams","LaunchQueue","OTPCredential","PaymentAddress","PaymentRequest","PaymentResponse","PaymentMethodChangeEvent","Presentation","PresentationAvailability","PresentationConnection","PresentationConnectionAvailableEvent","PresentationConnectionCloseEvent","PresentationConnectionList","PresentationReceiver","PresentationRequest","Serial","SerialPort","ToggleEvent","USB","USBAlternateInterface","USBConfiguration","USBConnectionEvent","USBDevice","USBEndpoint","USBInTransferResult","USBInterface","USBIsochronousInTransferPacket","USBIsochronousInTransferResult","USBIsochronousOutTransferPacket","USBIsochronousOutTransferResult","USBOutTransferResult","WakeLock","WakeLockSentinel","WindowControlsOverlay","WindowControlsOverlayGeometryChangeEvent","XRAnchor","XRAnchorSet","XRBoundedReferenceSpace","XRCPUDepthInformation","XRCamera","XRDepthInformation","XRFrame","XRHitTestResult","XRHitTestSource","XRInputSource","XRInputSourceArray","XRInputSourceEvent","XRInputSourcesChangeEvent","XRLightEstimate","XRLightProbe","XRPose","XRRay","XRReferenceSpace","XRReferenceSpaceEvent","XRRenderState","XRRigidTransform","XRSession","XRSessionEvent","XRSpace","XRSystem","XRTransientInputHitTestResult","XRTransientInputHitTestSource","XRView","XRViewerPose","XRViewport","XRWebGLDepthInformation","XRWebGLLayer","getScreenDetails","openDatabase","queryLocalFonts","showDirectoryPicker","showOpenFilePicker","showSaveFilePicker","AnimationPlaybackEvent","AnimationTimeline","CSSAnimation","CSSTransition","DocumentTimeline","BackgroundFetchManager","BackgroundFetchRecord","BackgroundFetchRegistration","BluetoothUUID","BrowserCaptureMediaStreamTrack","CropTarget","CSSStartingStyleRule","ContentVisibilityAutoStateChangeEvent","DocumentPictureInPictureEvent","Highlight","HighlightRegistry","MediaMetadata","MediaSession","MutationEvent","NavigatorUAData","Notification","PaymentManager","PaymentRequestUpdateEvent","PeriodicSyncManager","PermissionStatus","Permissions","PushManager","PushSubscription","PushSubscriptionOptions","RemotePlayback","ScrollTimeline","ViewTimeline","SharedWorker","SpeechSynthesisErrorEvent","SpeechSynthesisEvent","SpeechSynthesisUtterance","VideoPlaybackQuality","ViewTransition","VisibilityStateEntry","webkitSpeechGrammar","webkitSpeechGrammarList","webkitSpeechRecognition","webkitSpeechRecognitionError","webkitSpeechRecognitionEvent","webkitRequestFileSystem","webkitResolveLocalFileSystemURL"]},{"key":"String","proto":"String","instance":"String","props":["length","name","prototype"],"methods":["fromCharCode","fromCodePoint","raw"]},{"key":"Number","proto":"Number","instance":"Number","props":["length","name","prototype","MAX_VALUE","MIN_VALUE","NaN","NEGATIVE_INFINITY","POSITIVE_INFINITY","MAX_SAFE_INTEGER","MIN_SAFE_INTEGER","EPSILON"],"methods":["isFinite","isInteger","isNaN","isSafeInteger","parseFloat","parseInt"]},{"key":"Array","proto":"Array","instance":"Array","props":["length","name","prototype"],"methods":["isArray","from","of"]},{"key":"Object","proto":"Object","instance":"Object","props":["length","name","prototype"],"methods":["assign","getOwnPropertyDescriptor","getOwnPropertyDescriptors","getOwnPropertyNames","getOwnPropertySymbols","hasOwn","is","preventExtensions","seal","create","defineProperties","defineProperty","freeze","getPrototypeOf","setPrototypeOf","isExtensible","isFrozen","isSealed","keys","entries","fromEntries","values","groupBy"]},{"key":"Symbol","proto":"Symbol","instance":"Symbol","props":["length","name","prototype","asyncIterator","hasInstance","isConcatSpreadable","iterator","match","matchAll","replace","search","species","split","toPrimitive","toStringTag","unscopables"],"methods":["for","keyFor"]},{"key":"Math","proto":"Math","instance":"Math","props":["E","LN10","LN2","LOG10E","LOG2E","PI","SQRT1_2","SQRT2"],"methods":["abs","acos","acosh","asin","asinh","atan","atanh","atan2","ceil","cbrt","expm1","clz32","cos","cosh","exp","floor","fround","hypot","imul","log","log1p","log2","log10","max","min","pow","random","round","sign","sin","sinh","sqrt","tan","tanh","trunc"]},{"key":"Date","proto":"Date","instance":"Date","props":["length","name","prototype"],"methods":["now","parse","UTC"]},{"key":"Node","proto":"Node","instance":"Node","props":["length","name","arguments","caller","prototype","ELEMENT_NODE","ATTRIBUTE_NODE","TEXT_NODE","CDATA_SECTION_NODE","ENTITY_REFERENCE_NODE","ENTITY_NODE","PROCESSING_INSTRUCTION_NODE","COMMENT_NODE","DOCUMENT_NODE","DOCUMENT_TYPE_NODE","DOCUMENT_FRAGMENT_NODE","NOTATION_NODE","DOCUMENT_POSITION_DISCONNECTED","DOCUMENT_POSITION_PRECEDING","DOCUMENT_POSITION_FOLLOWING","DOCUMENT_POSITION_CONTAINS","DOCUMENT_POSITION_CONTAINED_BY","DOCUMENT_POSITION_IMPLEMENTATION_SPECIFIC"],"methods":[]},{"key":"JSON","proto":"JSON","instance":"JSON","props":[],"methods":["parse","stringify","rawJSON","isRawJSON"]},{"key":"Promise","proto":"Promise","instance":"Promise","props":["length","name","prototype"],"methods":["all","allSettled","any","race","resolve","reject"]},{"key":"Reflect","proto":"Reflect","instance":"Reflect","props":[],"methods":["defineProperty","deleteProperty","apply","construct","get","getOwnPropertyDescriptor","getPrototypeOf","has","isExtensible","ownKeys","preventExtensions","set","setPrototypeOf"]},{"key":"Intl","proto":"Intl","instance":"Intl","props":[],"methods":["getCanonicalLocales","supportedValuesOf","DateTimeFormat","NumberFormat","Collator","v8BreakIterator","PluralRules","RelativeTimeFormat","ListFormat","Locale","DisplayNames","Segmenter"]},{"key":"URL","proto":"URL","instance":"URL","props":["length","name","arguments","caller","prototype"],"methods":["createObjectURL","revokeObjectURL"]},{"key":"Window","proto":"Window","instance":"Window","props":["length","name","arguments","caller","prototype","TEMPORARY","PERSISTENT"],"methods":[]},{"key":"DOMException","proto":"DOMException","instance":"DOMException","props":["length","name","arguments","caller","prototype","INDEX_SIZE_ERR","DOMSTRING_SIZE_ERR","HIERARCHY_REQUEST_ERR","WRONG_DOCUMENT_ERR","INVALID_CHARACTER_ERR","NO_DATA_ALLOWED_ERR","NO_MODIFICATION_ALLOWED_ERR","NOT_FOUND_ERR","NOT_SUPPORTED_ERR","INUSE_ATTRIBUTE_ERR","INVALID_STATE_ERR","SYNTAX_ERR","INVALID_MODIFICATION_ERR","NAMESPACE_ERR","INVALID_ACCESS_ERR","VALIDATION_ERR","TYPE_MISMATCH_ERR","SECURITY_ERR","NETWORK_ERR","ABORT_ERR","URL_MISMATCH_ERR","QUOTA_EXCEEDED_ERR","TIMEOUT_ERR","INVALID_NODE_TYPE_ERR","DATA_CLONE_ERR"],"methods":[]},{"key":"location","proto":"location","instance":"location","props":["ancestorOrigins","href","origin","protocol","host","hostname","port","pathname","search","hash"],"methods":["valueOf","assign","reload","replace","toString"]},{"key":"console","proto":"console","instance":"console","props":["memory"],"methods":["debug","error","info","log","warn","dir","dirxml","table","trace","group","groupCollapsed","groupEnd","clear","count","countReset","assert","profile","profileEnd","time","timeLog","timeEnd","timeStamp","context","createTask"]},{"key":"Document::|document","proto":"Document::","instance":"document","props":["implementation","URL","documentURI","compatMode","characterSet","charset","inputEncoding","contentType","doctype","documentElement","xmlEncoding","xmlVersion","xmlStandalone","domain","referrer","cookie","lastModified","readyState","title","dir","body","head","images","embeds","plugins","links","forms","scripts","currentScript","defaultView","designMode","onreadystatechange","anchors","applets","fgColor","linkColor","vlinkColor","alinkColor","bgColor","all","scrollingElement","onpointerlockchange","onpointerlockerror","hidden","visibilityState","wasDiscarded","prerendering","featurePolicy","webkitVisibilityState","webkitHidden","onbeforecopy","onbeforecut","onbeforepaste","onfreeze","onprerenderingchange","onresume","onsearch","onvisibilitychange","fullscreenEnabled","fullscreen","onfullscreenchange","onfullscreenerror","webkitIsFullScreen","webkitCurrentFullScreenElement","webkitFullscreenEnabled","webkitFullscreenElement","onwebkitfullscreenchange","onwebkitfullscreenerror","rootElement","pictureInPictureEnabled","onbeforexrselect","onabort","onbeforeinput","onblur","oncancel","oncanplay","oncanplaythrough","onchange","onclick","onclose","oncontextlost","oncontextmenu","oncontextrestored","oncuechange","ondblclick","ondrag","ondragend","ondragenter","ondragleave","ondragover","ondragstart","ondrop","ondurationchange","onemptied","onended","onerror","onfocus","onformdata","oninput","oninvalid","onkeydown","onkeypress","onkeyup","onload","onloadeddata","onloadedmetadata","onloadstart","onmousedown","onmouseenter","onmouseleave","onmousemove","onmouseout","onmouseover","onmouseup","onmousewheel","onpause","onplay","onplaying","onprogress","onratechange","onreset","onresize","onscroll","onsecuritypolicyviolation","onseeked","onseeking","onselect","onslotchange","onstalled","onsubmit","onsuspend","ontimeupdate","ontoggle","onvolumechange","onwaiting","onwebkitanimationend","onwebkitanimationiteration","onwebkitanimationstart","onwebkittransitionend","onwheel","onauxclick","ongotpointercapture","onlostpointercapture","onpointerdown","onpointermove","onpointerrawupdate","onpointerup","onpointercancel","onpointerover","onpointerout","onpointerenter","onpointerleave","onselectstart","onselectionchange","onanimationend","onanimationiteration","onanimationstart","ontransitionrun","ontransitionstart","ontransitionend","ontransitioncancel","oncopy","oncut","onpaste","children","firstElementChild","lastElementChild","childElementCount","activeElement","styleSheets","pointerLockElement","fullscreenElement","adoptedStyleSheets","pictureInPictureElement","fonts","fragmentDirective","onbeforematch","onbeforetoggle","timeline","oncontentvisibilityautostatechange","onscrollend"],"methods":["adoptNode","append","captureEvents","caretRangeFromPoint","clear","close","createAttribute","createAttributeNS","createCDATASection","createComment","createDocumentFragment","createElement","createElementNS","createEvent","createExpression","createNSResolver","createNodeIterator","createProcessingInstruction","createRange","createTextNode","createTreeWalker","elementFromPoint","elementsFromPoint","evaluate","execCommand","exitFullscreen","exitPictureInPicture","exitPointerLock","getElementById","getElementsByClassName","getElementsByName","getElementsByTagName","getElementsByTagNameNS","getSelection","hasFocus","importNode","open","prepend","queryCommandEnabled","queryCommandIndeterm","queryCommandState","queryCommandSupported","queryCommandValue","querySelector","querySelectorAll","releaseEvents","replaceChildren","webkitCancelFullScreen","webkitExitFullscreen","write","writeln","constructor","hasPrivateToken","hasRedemptionRecord","getAnimations","hasStorageAccess","requestStorageAccess","startViewTransition"]},{"key":"Navigator::|navigator","proto":"Navigator::","instance":"navigator","props":["vendorSub","productSub","vendor","maxTouchPoints","scheduling","userActivation","doNotTrack","geolocation","connection","plugins","mimeTypes","pdfViewerEnabled","webkitTemporaryStorage","webkitPersistentStorage","hardwareConcurrency","cookieEnabled","appCodeName","appName","appVersion","platform","product","userAgent","language","languages","onLine","webdriver","bluetooth","clipboard","credentials","keyboard","managed","mediaDevices","storage","serviceWorker","virtualKeyboard","wakeLock","deviceMemory","ink","hid","locks","gpu","mediaCapabilities","mediaSession","permissions","presentation","usb","xr","serial","windowControlsOverlay","userAgentData"],"methods":["getGamepads","javaEnabled","sendBeacon","vibrate","constructor","canShare","share","clearAppBadge","getBattery","getUserMedia","requestMIDIAccess","requestMediaKeySystemAccess","setAppBadge","webkitGetUserMedia","getInstalledRelatedApps","registerProtocolHandler","unregisterProtocolHandler"]},{"key":"Screen::|screen","proto":"Screen::","instance":"screen","props":["availWidth","availHeight","width","height","colorDepth","pixelDepth","availLeft","availTop","orientation","onchange","isExtended"],"methods":["constructor"]},{"key":"History::|history","proto":"History::","instance":"history","props":["length","scrollRestoration","state"],"methods":["back","forward","go","pushState","replaceState","constructor"]},{"key":"Storage::|localStorage","proto":"Storage::","instance":"localStorage","props":["length"],"methods":["clear","getItem","key","removeItem","setItem","constructor"]},{"key":"Storage::|sessionStorage","proto":"Storage::","instance":"sessionStorage","props":["length"],"methods":["clear","getItem","key","removeItem","setItem","constructor"]},{"key":"Event::|event","proto":"Event::","instance":"event","props":["type","target","currentTarget","eventPhase","bubbles","cancelable","defaultPrevented","composed","timeStamp","srcElement","returnValue","cancelBubble","NONE","CAPTURING_PHASE","AT_TARGET","BUBBLING_PHASE"],"methods":["composedPath","initEvent","preventDefault","stopImmediatePropagation","stopPropagation","constructor"]},{"key":"Clipboard::|navigator.clipboard","proto":"Clipboard::","instance":"navigator.clipboard","props":[],"methods":["read","readText","write","writeText","constructor"]},{"key":"String::","proto":"String::","props":["length"],"methods":["constructor","anchor","at","big","blink","bold","charAt","charCodeAt","codePointAt","concat","endsWith","fontcolor","fontsize","fixed","includes","indexOf","italics","lastIndexOf","link","localeCompare","match","matchAll","normalize","padEnd","padStart","repeat","replace","replaceAll","search","slice","small","split","strike","sub","substr","substring","sup","startsWith","toString","trim","trimStart","trimLeft","trimEnd","trimRight","toLocaleLowerCase","toLocaleUpperCase","toLowerCase","toUpperCase","valueOf","isWellFormed","toWellFormed"]},{"key":"Number::","proto":"Number::","props":[],"methods":["constructor","toExponential","toFixed","toPrecision","toString","valueOf","toLocaleString"]},{"key":"Array::","proto":"Array::","props":["length"],"methods":["constructor","at","concat","copyWithin","fill","find","findIndex","findLast","findLastIndex","lastIndexOf","pop","push","reverse","shift","unshift","slice","sort","splice","includes","indexOf","join","keys","entries","values","forEach","filter","flat","flatMap","map","every","some","reduce","reduceRight","toLocaleString","toString","toReversed","toSorted","toSpliced","with"]},{"key":"RegExp::","proto":"RegExp::","props":["dotAll","flags","global","hasIndices","ignoreCase","multiline","source","sticky","unicode","unicodeSets"],"methods":["constructor","exec","compile","toString","test"]},{"key":"Date::","proto":"Date::","props":[],"methods":["constructor","toString","toDateString","toTimeString","toISOString","toUTCString","toGMTString","getDate","setDate","getDay","getFullYear","setFullYear","getHours","setHours","getMilliseconds","setMilliseconds","getMinutes","setMinutes","getMonth","setMonth","getSeconds","setSeconds","getTime","setTime","getTimezoneOffset","getUTCDate","setUTCDate","getUTCDay","getUTCFullYear","setUTCFullYear","getUTCHours","setUTCHours","getUTCMilliseconds","setUTCMilliseconds","getUTCMinutes","setUTCMinutes","getUTCMonth","setUTCMonth","getUTCSeconds","setUTCSeconds","valueOf","getYear","setYear","toJSON","toLocaleString","toLocaleDateString","toLocaleTimeString"]},{"key":"Node::","proto":"Node::","props":["nodeType","nodeName","baseURI","isConnected","ownerDocument","parentNode","parentElement","childNodes","firstChild","lastChild","previousSibling","nextSibling","nodeValue","textContent","ELEMENT_NODE","ATTRIBUTE_NODE","TEXT_NODE","CDATA_SECTION_NODE","ENTITY_REFERENCE_NODE","ENTITY_NODE","PROCESSING_INSTRUCTION_NODE","COMMENT_NODE","DOCUMENT_NODE","DOCUMENT_TYPE_NODE","DOCUMENT_FRAGMENT_NODE","NOTATION_NODE","DOCUMENT_POSITION_DISCONNECTED","DOCUMENT_POSITION_PRECEDING","DOCUMENT_POSITION_FOLLOWING","DOCUMENT_POSITION_CONTAINS","DOCUMENT_POSITION_CONTAINED_BY","DOCUMENT_POSITION_IMPLEMENTATION_SPECIFIC"],"methods":["appendChild","cloneNode","compareDocumentPosition","contains","getRootNode","hasChildNodes","insertBefore","isDefaultNamespace","isEqualNode","isSameNode","lookupNamespaceURI","lookupPrefix","normalize","removeChild","replaceChild","constructor"]},{"key":"Element::","proto":"Element::","props":["namespaceURI","prefix","localName","tagName","id","className","classList","slot","attributes","shadowRoot","part","assignedSlot","innerHTML","outerHTML","scrollTop","scrollLeft","scrollWidth","scrollHeight","clientTop","clientLeft","clientWidth","clientHeight","onbeforecopy","onbeforecut","onbeforepaste","onsearch","elementTiming","onfullscreenchange","onfullscreenerror","onwebkitfullscreenchange","onwebkitfullscreenerror","role","ariaAtomic","ariaAutoComplete","ariaBusy","ariaBrailleLabel","ariaBrailleRoleDescription","ariaChecked","ariaColCount","ariaColIndex","ariaColSpan","ariaCurrent","ariaDescription","ariaDisabled","ariaExpanded","ariaHasPopup","ariaHidden","ariaInvalid","ariaKeyShortcuts","ariaLabel","ariaLevel","ariaLive","ariaModal","ariaMultiLine","ariaMultiSelectable","ariaOrientation","ariaPlaceholder","ariaPosInSet","ariaPressed","ariaReadOnly","ariaRelevant","ariaRequired","ariaRoleDescription","ariaRowCount","ariaRowIndex","ariaRowSpan","ariaSelected","ariaSetSize","ariaSort","ariaValueMax","ariaValueMin","ariaValueNow","ariaValueText","children","firstElementChild","lastElementChild","childElementCount","previousElementSibling","nextElementSibling"],"methods":["after","animate","append","attachShadow","before","closest","computedStyleMap","getAttribute","getAttributeNS","getAttributeNames","getAttributeNode","getAttributeNodeNS","getBoundingClientRect","getClientRects","getElementsByClassName","getElementsByTagName","getElementsByTagNameNS","getInnerHTML","hasAttribute","hasAttributeNS","hasAttributes","hasPointerCapture","insertAdjacentElement","insertAdjacentHTML","insertAdjacentText","matches","prepend","querySelector","querySelectorAll","releasePointerCapture","remove","removeAttribute","removeAttributeNS","removeAttributeNode","replaceChildren","replaceWith","requestFullscreen","requestPointerLock","scroll","scrollBy","scrollIntoView","scrollIntoViewIfNeeded","scrollTo","setAttribute","setAttributeNS","setAttributeNode","setAttributeNodeNS","setPointerCapture","toggleAttribute","webkitMatchesSelector","webkitRequestFullScreen","webkitRequestFullscreen","checkVisibility","getAnimations","constructor","setHTML"]},{"key":"HTMLElement::","proto":"HTMLElement::","props":["title","lang","translate","dir","hidden","accessKey","draggable","spellcheck","textprediction","autocapitalize","contentEditable","enterKeyHint","isContentEditable","inputMode","virtualKeyboardPolicy","offsetParent","offsetTop","offsetLeft","offsetWidth","offsetHeight","innerText","outerText","onbeforexrselect","onabort","onbeforeinput","onblur","oncancel","oncanplay","oncanplaythrough","onchange","onclick","onclose","oncontextlost","oncontextmenu","oncontextrestored","oncuechange","ondblclick","ondrag","ondragend","ondragenter","ondragleave","ondragover","ondragstart","ondrop","ondurationchange","onemptied","onended","onerror","onfocus","onformdata","oninput","oninvalid","onkeydown","onkeypress","onkeyup","onload","onloadeddata","onloadedmetadata","onloadstart","onmousedown","onmouseenter","onmouseleave","onmousemove","onmouseout","onmouseover","onmouseup","onmousewheel","onpause","onplay","onplaying","onprogress","onratechange","onreset","onresize","onscroll","onsecuritypolicyviolation","onseeked","onseeking","onselect","onslotchange","onstalled","onsubmit","onsuspend","ontimeupdate","ontoggle","onvolumechange","onwaiting","onwebkitanimationend","onwebkitanimationiteration","onwebkitanimationstart","onwebkittransitionend","onwheel","onauxclick","ongotpointercapture","onlostpointercapture","onpointerdown","onpointermove","onpointerrawupdate","onpointerup","onpointercancel","onpointerover","onpointerout","onpointerenter","onpointerleave","onselectstart","onselectionchange","onanimationend","onanimationiteration","onanimationstart","ontransitionrun","ontransitionstart","ontransitionend","ontransitioncancel","oncopy","oncut","onpaste","dataset","nonce","autofocus","tabIndex","style","attributeStyleMap","inert","oncontentvisibilityautostatechange","onscrollend","popover","onbeforetoggle","onbeforematch"],"methods":["attachInternals","blur","click","focus","constructor","hidePopover","showPopover","togglePopover"]},{"key":"Function::","proto":"Function::","props":["length","name","arguments","caller"],"methods":["constructor","apply","bind","call","toString"]},{"key":"Promise::","proto":"Promise::","props":[],"methods":["constructor","then","catch","finally"]},{"key":"EventTarget::","proto":"EventTarget::","props":[],"methods":["addEventListener","dispatchEvent","removeEventListener","constructor"]},{"key":"Crypto::|crypto","proto":"Crypto::","instance":"crypto","props":["subtle"],"methods":["getRandomValues","constructor","randomUUID"]},{"key":"Selection::","proto":"Selection::","props":["anchorNode","anchorOffset","focusNode","focusOffset","isCollapsed","rangeCount","type","baseNode","baseOffset","extentNode","extentOffset"],"methods":["addRange","collapse","collapseToEnd","collapseToStart","containsNode","deleteFromDocument","empty","extend","getRangeAt","modify","removeAllRanges","removeRange","selectAllChildren","setBaseAndExtent","setPosition","toString","constructor"]},{"key":"CanvasRenderingContext2D::","proto":"CanvasRenderingContext2D::","props":["canvas","globalAlpha","globalCompositeOperation","filter","imageSmoothingEnabled","imageSmoothingQuality","strokeStyle","fillStyle","shadowOffsetX","shadowOffsetY","shadowBlur","shadowColor","lineWidth","lineCap","lineJoin","miterLimit","lineDashOffset","font","textAlign","textBaseline","direction","fontKerning","fontStretch","fontVariantCaps","letterSpacing","textRendering","wordSpacing"],"methods":["clip","createConicGradient","createImageData","createLinearGradient","createPattern","createRadialGradient","drawFocusIfNeeded","drawImage","fill","fillText","getContextAttributes","getImageData","getLineDash","getTransform","isContextLost","isPointInPath","isPointInStroke","measureText","putImageData","reset","roundRect","save","scale","setLineDash","setTransform","stroke","strokeText","transform","translate","arc","arcTo","beginPath","bezierCurveTo","clearRect","closePath","ellipse","fillRect","lineTo","moveTo","quadraticCurveTo","rect","resetTransform","restore","rotate","strokeRect","constructor"]},{"key":"FormData::","proto":"FormData::","props":[],"methods":["append","delete","get","getAll","has","set","entries","forEach","keys","values","constructor"]},{"key":"Response::","proto":"Response::","props":["type","url","redirected","status","ok","statusText","headers","body","bodyUsed"],"methods":["arrayBuffer","blob","clone","formData","json","text","constructor"]},{"key":"FileReader::","proto":"FileReader::","props":["readyState","result","error","onloadstart","onprogress","onload","onabort","onerror","onloadend","EMPTY","LOADING","DONE"],"methods":["abort","readAsArrayBuffer","readAsBinaryString","readAsDataURL","readAsText","constructor"]},{"key":"File::","proto":"File::","props":["name","lastModified","lastModifiedDate","webkitRelativePath"],"methods":["constructor"]},{"key":"Blob::","proto":"Blob::","props":["size","type"],"methods":["arrayBuffer","slice","stream","text","constructor"]},{"key":"HTMLMediaElement::","proto":"HTMLMediaElement::","props":["error","src","currentSrc","crossOrigin","networkState","preload","buffered","readyState","seeking","currentTime","duration","paused","defaultPlaybackRate","playbackRate","played","seekable","ended","autoplay","loop","preservesPitch","controls","controlsList","volume","muted","defaultMuted","textTracks","webkitAudioDecodedByteCount","webkitVideoDecodedByteCount","onencrypted","onwaitingforkey","srcObject","NETWORK_EMPTY","NETWORK_IDLE","NETWORK_LOADING","NETWORK_NO_SOURCE","HAVE_NOTHING","HAVE_METADATA","HAVE_CURRENT_DATA","HAVE_FUTURE_DATA","HAVE_ENOUGH_DATA","sinkId","remote","disableRemotePlayback","mediaKeys"],"methods":["addTextTrack","canPlayType","captureStream","load","pause","play","setSinkId","constructor","setMediaKeys"]},{"key":"HTMLCanvasElement::","proto":"HTMLCanvasElement::","props":["width","height"],"methods":["captureStream","getContext","toBlob","toDataURL","transferControlToOffscreen","constructor"]},{"key":"BatteryManager::","proto":"BatteryManager::","props":["charging","chargingTime","dischargingTime","level","onchargingchange","onchargingtimechange","ondischargingtimechange","onlevelchange"],"methods":["constructor"]}]
